efleetscheduler/__init__.py
efleetscheduler/generate_graphs.py
efleetscheduler/schedule_configure.py
efleetscheduler/schedule_generator_1.py
efleetscheduler/schedule_generator_2.py
efleetscheduler-1.0.4.dist-info/METADATA
efleetscheduler-1.0.4.dist-info/WHEEL
efleetscheduler-1.0.4.dist-info/licenses/LICENSE
efleetscheduler-1.0.4.dist-info/RECORD
