Metadata-Version: 2.4
Name: efleetscheduler
Version: 1.0.4
Summary: Electric Fleet Scheduling Optimization Tool
Project-URL: Homepage, https://github.com/mcarolinagilr/eFleetScheduler
Project-URL: Issues, https://github.com/mcarolinagilr/eFleetScheduler/issues
Author-email: Carolina Gil Ribeiro <mcarolinagilr@gmail.com>
License-Expression: MIT
License-File: LICENSE
Classifier: Development Status :: 3 - Alpha
Classifier: Intended Audience :: Science/Research
Classifier: License :: OSI Approved :: MIT License
Classifier: Operating System :: OS Independent
Classifier: Programming Language :: Python :: 3
Requires-Python: >=3.11
Requires-Dist: matplotlib>=3.3.0
Requires-Dist: numpy>=1.20.0
Requires-Dist: pandas>=1.3.0
Requires-Dist: xlsxwriter>=3.0.0
Provides-Extra: dev
Requires-Dist: jupyter>=1.0.0; extra == 'dev'
Requires-Dist: jupyterlab>=4.0.0; extra == 'dev'
Requires-Dist: pytest>=6.0.0; extra == 'dev'
